units_QBD/__init__.py
units_QBD/const.py
units_QBD/standardise_.py
units_QBD/tools.py
units_QBD-0.0.11.dist-info/METADATA
units_QBD-0.0.11.dist-info/WHEEL
units_QBD-0.0.11.dist-info/top_level.txt
units_QBD-0.0.11.dist-info/RECORD
